{
  "tag": "Back Beauty",
  "subject": "a elegant back beauty female model",
  "body": "hot glamour model, elegant back, dramatic shoulder line, back goddess",
  "outfit": "open back editorial, backless luxury dress, spine emphasis",
  "material": "liquid satin backless fabric, open back textile",
  "environment": "luxury interior, dramatic architecture, elegant space",
  "lighting": "strong rim backlight, back definition, elegant atmosphere",
  "style": "back beauty editorial, elegant fashion photography",
  "quality": "shot on Hasselblad H6D, warm golden film grade, portrait 2:3 vertical"
}