{
  "tag": "Rain Soaked",
  "subject": "a dramatic rain soaked female model",
  "body": "hot glamour model, narrow cinched waist, wide round hips, wet goddess",
  "outfit": "minimal soaking wet outfit, rain-drenched glamour, wet editorial",
  "material": "wet-look spandex, soaking wet appearance",
  "environment": "dramatic rain, wet urban street, city lights reflection",
  "lighting": "rain-soaked neon reflections, wet pavement glow, dramatic rain",
  "style": "rain soaked editorial, wet glamour photography",
  "quality": "shot on Sony A7R V, dark moody color grade, portrait 2:3 vertical"
}