{
  "tag": "Ruins Goddess",
  "subject": "a mysterious ruins goddess female model",
  "body": "hot glamour model, dramatic curves, ancient ruins goddess",
  "outfit": "ruins goddess editorial, ancient draped minimal styling",
  "material": "ancient draped fabric, ruins textile",
  "environment": "ancient ruins, crumbling columns, overgrown with nature",
  "lighting": "dramatic golden hour through ruins, ancient atmosphere",
  "style": "ruins goddess editorial, ancient world photography",
  "quality": "shot on Canon EOS R5, warm golden film grade, portrait 2:3 vertical"
}