{
  "tag": "Stewardess Dark",
  "subject": "a seductive female model in dark version stewardess uniform",
  "outfit": "ultra-fitted stewardess uniform, very short skirt, black stockings, stilettos, hat tilted",
  "material": "fitted uniform fabric, silk stockings",
  "environment": "private jet interior at night, dim cabin lighting, luxury seats",
  "lighting": "dim moody private jet cabin light, intimate atmosphere",
  "style": "dark stewardess fashion editorial, private jet fantasy",
  "quality": "ultra-sharp, 8K, professional fashion photography"
}