{
  "tag": "Succubus Anime",
  "subject": "a seductive succubus anime female model",
  "body": "super glamour model, tiny waist, very wide round hips, maximum hourglass demonic silhouette",
  "outfit": "succubus costume, dark wings, demon horns, revealing dark lingerie-inspired outfit, tail",
  "material": "glossy black latex-look fabric, dark feather wings, ornate demonic accessories",
  "environment": "dark demonic realm, hellfire backdrop, mysterious dark atmosphere",
  "lighting": "hellfire glow from below, dramatic demonic atmosphere, dark seductive light",
  "style": "succubus dark glamour editorial, demonic fantasy photography",
  "quality": "shot on Leica SL2, dark hellfire grade, portrait 2:3 vertical"
}